macromini/__init__.py
macromini/__main__.py
macromini/cli.py
macromini/git_utils.py
macromini/reviewer.py
macromini/agents/__init__.py
macromini/agents/base_agent.py
macromini/agents/performance_agent.py
macromini/agents/quality_agent.py
macromini/agents/security_agent.py
macromini/agents/style_agent.py
macromini/agents/testing_agent.py
macromini/orchestration/__init__.py
macromini/orchestration/aggregator.py
macromini/orchestration/graph.py
macromini/orchestration/router.py
macromini/orchestration/state.py
macromini/security/__init__.py
macromini/security/input_sanitizer.py
macromini-0.1.0.dist-info/licenses/LICENSE
macromini-0.1.0.dist-info/METADATA
macromini-0.1.0.dist-info/WHEEL
macromini-0.1.0.dist-info/entry_points.txt
macromini-0.1.0.dist-info/top_level.txt
macromini-0.1.0.dist-info/RECORD
