Metadata-Version: 2.4
Name: macromini
Version: 0.1.0
Summary: Multi-Agent Code Review Orchestration - Fully local code review powered by specialized AI agents
Author-email: Sharvil Chirputkar <sharvilchirputkar@gmail.com>
License: MIT
Project-URL: Homepage, https://github.com/chirpishere/macromini
Project-URL: Documentation, https://github.com/chirpishere/macromini#readme
Project-URL: Repository, https://github.com/chirpishere/macromini
Project-URL: Bug Tracker, https://github.com/chirpishere/macromini/issues
Keywords: code-review,ai,multi-agent,git,code-quality,langgraph
Classifier: Development Status :: 3 - Alpha
Classifier: Intended Audience :: Developers
Classifier: Topic :: Software Development :: Quality Assurance
Classifier: Topic :: Software Development :: Version Control :: Git
Classifier: License :: OSI Approved :: MIT License
Classifier: Programming Language :: Python :: 3
Classifier: Programming Language :: Python :: 3.9
Classifier: Programming Language :: Python :: 3.10
Classifier: Programming Language :: Python :: 3.11
Classifier: Programming Language :: Python :: 3.12
Classifier: Programming Language :: Python :: 3.13
Requires-Python: >=3.9
License-File: LICENSE
Requires-Dist: rich>=13.0.0
Requires-Dist: langchain-ollama>=0.1.0
Requires-Dist: langgraph>=0.2.0
Requires-Dist: GitPython>=3.1.0
Provides-Extra: dev
Requires-Dist: pytest>=7.0.0; extra == "dev"
Requires-Dist: black>=23.0.0; extra == "dev"
Requires-Dist: ruff>=0.1.0; extra == "dev"
Dynamic: license-file
